{
  "id": "observability-suite-expansion",
  "type": "epic",
  "title": "Observability Suite Expansion",
  "description": "Expand monitoring beyond existing PostgreSQL/Redis/Kubernetes templates. Add: SLO/SLI tracking, Kafka, Elasticsearch, MongoDB, RabbitMQ, APM/tracing, synthetic monitoring, log aggregation, anomaly detection, continuous profiling. Note: PostgreSQL/Redis/Kubernetes templates already implemented.",
  "status": "closed",
  "priority": "P1",
  "tags": [],
  "created_at": "2025-12-01T21:20:18.601281Z",
  "updated_at": "2025-12-22T11:18:07.464453Z",
  "legacy_id": "trellis-7pw",
  "closed_at": "2025-12-22T11:17:25.605021Z"
}
