{
  "id": "service-catalog-integration",
  "type": "epic",
  "title": "Service Catalog Integration",
  "description": "Optional integration with service catalogs (Backstage, Cortex, Port). Three usage modes: 1) Standalone (Git+YAML, no catalog required), 2) With Catalog (sync metadata from Backstage), 3) Hybrid (catalog + overrides). Key differentiator: 'Catalogs make you adopt their platform first. NthLayer works Day 1.'",
  "status": "open",
  "priority": "P3",
  "tags": [],
  "created_at": "2025-12-04T16:00:00Z",
  "updated_at": "2025-12-22T11:18:07.477933Z",
  "legacy_id": "trellis-catalog",
  "comments": [
    {
      "author": "scope-review",
      "text": "Deferred: Service Catalog Integration (optional)",
      "date": "2025-12-22T11:18:07Z"
    }
  ]
}
